<?xml version="1.0" encoding="UTF-8" standalone="yes"?><imgdir name="01142415.img"><imgdir name="info"><canvas name="icon" width="21" height="30"><vector name="origin" x="-5" y="30"/><string name="_hash" value="abc625d54472a8fdd4ac66238dbc53534f77216744c267705c493cc05a808ef0"/></canvas><canvas name="iconRaw" width="30" height="30"><vector name="origin" x="0" y="30"/><string name="_hash" value="dd6766e5acd335928b97e842cd73def443d358e0a10a63dfbbb476c5761e3c4d"/></canvas><string name="islot" value="Me"/><string name="vslot" value="Me"/><int name="reqJob" value="0"/><int name="reqLevel" value="1"/><int name="reqSTR" value="0"/><int name="reqDEX" value="0"/><int name="reqINT" value="0"/><int name="reqLUK" value="0"/><int name="incSTR" value="3"/><int name="incDEX" value="3"/><int name="incINT" value="3"/><int name="incLUK" value="3"/><int name="incPAD" value="2"/><int name="incMAD" value="2"/><int name="incMHP" value="100"/><int name="incMMP" value="100"/><int name="tuc" value="0"/><int name="price" value="0"/><int name="tradeBlock" value="1"/><int name="notSale" value="1"/><int name="only" value="1"/><int name="cash" value="0"/><int name="medalTag" value="285"/></imgdir></imgdir>