<?xml version="1.0" encoding="UTF-8" standalone="yes"?><imgdir name="9402210.img"><imgdir name="info"><int name="removeAfter" value="1"/><int name="hideName" value="1"/><imgdir name="revive"><int name="0" value="9402211"/></imgdir><int name="noFlip" value="1"/><int name="level" value="1"/><int name="maxHP" value="40000"/><int name="PADamage" value="3"/><int name="PDRate" value="25"/><int name="MADamage" value="1"/><int name="MDRate" value="25"/><int name="acc" value="500"/><int name="pushed" value="1"/><float name="fs" value="10.0"/><int name="boss" value="1"/><int name="summonType" value="12"/><int name="category" value="4"/><string name="mobType" value="7N"/></imgdir><imgdir name="stand"><canvas name="0" width="76" height="108"><vector name="origin" x="37" y="108"/><vector name="head" x="-89" y="-335"/><int name="delay" value="150"/><string name="_hash" value="b2c22369bf54efdebb26e14458780ff10ce923e80fb5366639ad949fcaed3bdf"/></canvas></imgdir><imgdir name="hit1"><canvas name="0" width="1" height="1"><vector name="origin" x="37" y="108"/><vector name="head" x="-89" y="-335"/><int name="delay" value="150"/><string name="_inlink" value="stand/0"/></canvas></imgdir><imgdir name="die1"><canvas name="0" width="1" height="1"><vector name="origin" x="37" y="108"/><vector name="head" x="-89" y="-335"/><int name="delay" value="150"/><string name="_inlink" value="stand/0"/></canvas><canvas name="1" width="112" height="140"><vector name="origin" x="52" y="99"/><vector name="head" x="-89" y="-335"/><int name="delay" value="150"/><string name="_hash" value="38fec632a81d351471ced91825b2f0db2fd935e34e51132e9a9fef8ea6786d66"/></canvas><canvas name="2" width="108" height="132"><vector name="origin" x="53" y="99"/><vector name="head" x="-89" y="-335"/><int name="delay" value="150"/><string name="_hash" value="cfe869fbf909465e5dd566e18769e8b02f46f6529e3261bdd691deca9ba1b52d"/></canvas><canvas name="3" width="148" height="136"><vector name="origin" x="70" y="97"/><vector name="head" x="-89" y="-335"/><int name="delay" value="150"/><string name="_hash" value="2bb0c223bc0d1d247c81646c9857f9895cc455a84c529bf8de338c3cee95883b"/></canvas><canvas name="4" width="140" height="128"><vector name="origin" x="68" y="93"/><vector name="head" x="-89" y="-335"/><int name="delay" value="150"/><string name="_hash" value="69e86d1aa816165486e582e5b4ab337b1ce256c3390a459023d3bfd657550e39"/></canvas><canvas name="5" width="128" height="120"><vector name="origin" x="62" y="89"/><vector name="head" x="-89" y="-335"/><int name="delay" value="150"/><string name="_hash" value="07b073a4a58dabab0e752ce5cfe8e46deffbb7dd92f696f901a3d3c067769210"/></canvas><canvas name="6" width="124" height="112"><vector name="origin" x="60" y="85"/><vector name="head" x="-89" y="-335"/><int name="delay" value="150"/><string name="_hash" value="eccafda0d9a8ef26901a1045bef626429879a6153939f6f45b9c2b126421932c"/></canvas><canvas name="7" width="116" height="128"><vector name="origin" x="57" y="86"/><vector name="head" x="-89" y="-335"/><int name="delay" value="150"/><string name="_hash" value="47f28a9f5c29826a1b4c8b6a5e8bfd8dfad1147f49bf94f0c008740c6d9bc309"/></canvas><canvas name="8" width="124" height="172"><vector name="origin" x="60" y="110"/><vector name="head" x="-89" y="-335"/><int name="delay" value="150"/><string name="_hash" value="e23e1e62ac4dbaafe978bf694107e1e60fae4eeb3d52934757009b39e49108fa"/></canvas><canvas name="9" width="152" height="188"><vector name="origin" x="77" y="124"/><vector name="head" x="-89" y="-335"/><int name="delay" value="150"/><string name="_hash" value="c897e7f6c7cfc69581867a87ebc8ac7c5273ff97fb26451f0d0b6d495f5b07ea"/></canvas><canvas name="10" width="152" height="184"><vector name="origin" x="80" y="121"/><vector name="head" x="-89" y="-335"/><int name="delay" value="150"/><string name="_hash" value="4319322996e73cfb784a0fc530bdb0d8fa7d6e0506aca284d57b4ef55df427c0"/></canvas><canvas name="11" width="148" height="180"><vector name="origin" x="78" y="122"/><vector name="head" x="-89" y="-335"/><int name="delay" value="150"/><string name="_hash" value="a363c553a1ab08f323d4bce417d4c2813d603bc13f009371ea9c1b64b134743b"/></canvas><canvas name="12" width="160" height="168"><vector name="origin" x="80" y="116"/><vector name="head" x="-89" y="-335"/><int name="delay" value="150"/><string name="_hash" value="25cb1d2b9d87e018ca4114a6170f6bcc7d5f0b65ccff3feeb9c93ebe3622c292"/></canvas><canvas name="13" width="180" height="152"><vector name="origin" x="79" y="108"/><vector name="head" x="-89" y="-335"/><int name="delay" value="150"/><string name="_hash" value="b9830e9f8081f3e47053e5a683e0b537fb059414b1f3b15c58c134af73a70b85"/></canvas><canvas name="14" width="200" height="140"><vector name="origin" x="93" y="100"/><vector name="head" x="-89" y="-335"/><int name="delay" value="150"/><string name="_hash" value="267f9f17a6656078a89e95c89169d5f11bc648bf762084b0503844dd174d6c74"/></canvas><canvas name="15" width="224" height="136"><vector name="origin" x="104" y="97"/><vector name="head" x="-89" y="-335"/><int name="delay" value="150"/><string name="_hash" value="c1c70a27d86178f595ebdea41393269364f188986e86922a3ebc36c6f59dbbd9"/></canvas><canvas name="16" width="236" height="128"><vector name="origin" x="112" y="94"/><vector name="head" x="-89" y="-335"/><int name="delay" value="150"/><string name="_hash" value="02827a999a1e51176813f518f62885bca5e631ccad6bce9acb91ca3b34e50569"/></canvas><canvas name="17" width="244" height="120"><vector name="origin" x="115" y="90"/><vector name="head" x="-89" y="-335"/><int name="delay" value="150"/><string name="_hash" value="b87ba7f5f57b4fc41199a7f16bf90f4995bfd5c41f5c4337647358b64b567a82"/></canvas><canvas name="18" width="252" height="192"><vector name="origin" x="112" y="165"/><vector name="head" x="-89" y="-335"/><int name="delay" value="150"/><string name="_hash" value="a4fd55a9897368cd848ebd509acb43cf765a3494a2ac8275af088e7afe0ba29f"/></canvas><canvas name="19" width="268" height="272"><vector name="origin" x="120" y="241"/><vector name="head" x="-89" y="-335"/><int name="delay" value="150"/><string name="_hash" value="1afd90fab79a389fe316d110d5836f277b5913bd3c33974896af07567a667e55"/></canvas><canvas name="20" width="288" height="276"><vector name="origin" x="136" y="263"/><vector name="head" x="-89" y="-335"/><int name="delay" value="150"/><string name="_hash" value="4f67fe416c35bbddc7ce885de94836803ca2200b45741cf666912141b8500c24"/></canvas><canvas name="21" width="556" height="512"><vector name="origin" x="298" y="505"/><vector name="head" x="-89" y="-335"/><int name="delay" value="150"/><string name="_hash" value="35cb6fe205fc2c87dc0cb407f015de4f75d134428e670c3727676faa46cf8500"/></canvas><canvas name="22" width="700" height="520"><vector name="origin" x="362" y="512"/><vector name="head" x="-89" y="-335"/><int name="delay" value="150"/><string name="_hash" value="00d9f99a86b8f407768002002366a80ffbc237ef8e818072125fdca2c0be48c5"/></canvas><canvas name="23" width="700" height="516"><vector name="origin" x="362" y="512"/><vector name="head" x="-89" y="-335"/><int name="delay" value="150"/><string name="_hash" value="cc630e2462b6c7f3309f0a625590fa6de449f4a29655776c8d3f76bfd9ce9d8e"/></canvas><canvas name="24" width="620" height="520"><vector name="origin" x="325" y="513"/><vector name="head" x="-89" y="-335"/><int name="delay" value="150"/><string name="_hash" value="20002f722b09613ca2fb7512b82551395215f405dcb6573a74e0b335ef06c37a"/></canvas><canvas name="25" width="612" height="520"><vector name="origin" x="322" y="515"/><vector name="head" x="-89" y="-335"/><int name="delay" value="150"/><string name="_hash" value="9af807525aae3d6a88a972815295ca38d1e92144433176d85986af1e673d6bf7"/></canvas><canvas name="26" width="612" height="520"><vector name="origin" x="322" y="516"/><vector name="head" x="-89" y="-335"/><int name="delay" value="150"/><string name="_hash" value="3ccaa5cf99077754982213df31391e4783d1a600ef64f7228aad9afd0c0081ab"/></canvas><canvas name="27" width="620" height="516"><vector name="origin" x="325" y="515"/><vector name="head" x="-89" y="-335"/><int name="delay" value="150"/><string name="_hash" value="6bfd8dc01b84c917dfa2720f2bee8afaec5754a6eb121e7d63bfc9ee2db3edb5"/></canvas><canvas name="28" width="612" height="464"><vector name="origin" x="322" y="461"/><vector name="head" x="-89" y="-335"/><int name="delay" value="150"/><string name="_hash" value="a57bf987f06986945823c4ecc6f39dc76ac66ec2a1a5af70a26cfcb33898f010"/></canvas><canvas name="29" width="616" height="468"><vector name="origin" x="324" y="465"/><vector name="head" x="-89" y="-335"/><int name="delay" value="150"/><string name="_hash" value="1a8f9a0f40723439af18c76904b4f23d0c83e56e0457a552ac3d126ed1e523e2"/></canvas><canvas name="30" width="620" height="468"><vector name="origin" x="325" y="465"/><vector name="head" x="-89" y="-335"/><int name="delay" value="150"/><string name="_hash" value="f012de6ce056901f63eb35f21d81703bbcd2858a6687237dc008083d16c4d4f2"/></canvas><canvas name="31" width="616" height="468"><vector name="origin" x="324" y="465"/><vector name="head" x="-89" y="-335"/><int name="delay" value="150"/><string name="_hash" value="2cd870ebc6a757532c9be4730d59b93f68eeb178808baef80633bb6b1c5112b5"/></canvas><canvas name="32" width="620" height="468"><vector name="origin" x="325" y="465"/><vector name="head" x="-89" y="-335"/><int name="delay" value="150"/><string name="_hash" value="1430f624a9ad15b3a120162bb0437ebfbb21780dc4d71680689da24662fb9de9"/></canvas><canvas name="33" width="616" height="468"><vector name="origin" x="324" y="465"/><vector name="head" x="-89" y="-335"/><int name="delay" value="150"/><string name="_hash" value="d12d4f4e3d7667920895cc929e2fdf6e92a385fb440ebb15362c602714e26685"/></canvas><canvas name="34" width="620" height="468"><vector name="origin" x="325" y="465"/><vector name="head" x="-89" y="-335"/><int name="delay" value="150"/><string name="_hash" value="8beaf17762a675c4beca43f7d8cd9b5c6569e2f371956dd89915d5eb90d88dc5"/></canvas><canvas name="35" width="616" height="468"><vector name="origin" x="324" y="465"/><vector name="head" x="-89" y="-335"/><int name="delay" value="150"/><string name="_hash" value="d933cae29591fc92dd6fc33f7df2b5e8750b59fc92a6be38db4c2094e8b67cc8"/></canvas><canvas name="36" width="1" height="1"><vector name="origin" x="325" y="465"/><vector name="head" x="-89" y="-335"/><int name="delay" value="150"/><string name="_inlink" value="die1/34"/></canvas><canvas name="37" width="1" height="1"><vector name="origin" x="324" y="465"/><vector name="head" x="-89" y="-335"/><int name="delay" value="150"/><string name="_inlink" value="die1/35"/></canvas><canvas name="38" width="1" height="1"><vector name="origin" x="325" y="465"/><vector name="head" x="-89" y="-335"/><int name="delay" value="150"/><string name="_inlink" value="die1/34"/></canvas><canvas name="39" width="1" height="1"><vector name="origin" x="324" y="465"/><vector name="head" x="-89" y="-335"/><int name="delay" value="150"/><string name="_inlink" value="die1/35"/></canvas><canvas name="40" width="1" height="1"><vector name="origin" x="325" y="465"/><vector name="head" x="-89" y="-335"/><int name="delay" value="330"/><string name="_inlink" value="die1/34"/></canvas></imgdir></imgdir>