<?xml version="1.0" encoding="UTF-8" standalone="yes"?><imgdir name="9201520.img"><imgdir name="info"><int name="hide" value="1"/></imgdir><imgdir name="stand"><canvas name="0" width="84" height="81"><vector name="origin" x="41" y="78"/><int name="z" value="0"/><string name="_hash" value="68c9159fed9d28908ed3430fe0653fd5e174203a72f7425a34b2fffc8c4eb46a"/></canvas><canvas name="1" width="84" height="81"><vector name="origin" x="41" y="78"/><int name="z" value="0"/><string name="_hash" value="b9e6d7f64290e5e323de91f0f70c5960dd3e5426d00673648a47763a29815f07"/></canvas><canvas name="2" width="84" height="81"><vector name="origin" x="41" y="78"/><int name="z" value="0"/><string name="_hash" value="730aa93bad9a9702daba614fb909ca2026d6dc528170d77672d8eb057b9686fd"/></canvas><canvas name="3" width="84" height="81"><vector name="origin" x="41" y="78"/><int name="z" value="0"/><string name="_hash" value="ab15d2f83b5feba51b9aab166527bf3d5bd3afac538dac76a5aa25ac06108b23"/></canvas><canvas name="4" width="84" height="81"><vector name="origin" x="41" y="78"/><int name="z" value="0"/><string name="_hash" value="44218c65b19c3b9b262ca4d67ff1d95451907bb1830a69c36335b34264f0cb7d"/></canvas><canvas name="5" width="84" height="81"><vector name="origin" x="41" y="78"/><int name="z" value="0"/><string name="_hash" value="704f046618a673d6f109e50340d5df70bf167ba6871180f14efdfc4d1bb8f0ef"/></canvas><canvas name="6" width="84" height="81"><vector name="origin" x="41" y="78"/><int name="z" value="0"/><string name="_hash" value="430e4cbe33cf18f72a78f220c6f7e522a0cdd259ad951adba6eaa734f288403b"/></canvas><canvas name="7" width="84" height="81"><vector name="origin" x="41" y="78"/><int name="z" value="0"/><string name="_hash" value="61b2cb6b220d825b672c0da532db9342bd2cda9ee8fc5b0758e9d76c5b9e47f6"/></canvas></imgdir><imgdir name="say"><canvas name="0" width="84" height="81"><vector name="origin" x="41" y="78"/><int name="z" value="0"/><string name="_hash" value="ac99ee8777c1d9fa9a284923dccdf84a549d3176c909696976b18004d4c43e45"/></canvas><canvas name="1" width="84" height="81"><vector name="origin" x="41" y="78"/><int name="z" value="0"/><string name="_hash" value="88d95d7c6035102c5a6520dd6556dd4eb17e0041401ea81305bfaa67f13367ee"/></canvas><canvas name="2" width="84" height="81"><vector name="origin" x="41" y="78"/><int name="z" value="0"/><string name="_hash" value="84acf4c1066dfbb8706e31179bec8968bcec688fc6e98b28b37967700b738488"/></canvas><canvas name="3" width="84" height="81"><vector name="origin" x="41" y="78"/><int name="z" value="0"/><string name="_hash" value="9d8103070b30f6df1af404c99b8ac1b7803e508567d69cac892cfecc04ad92be"/></canvas><canvas name="4" width="84" height="81"><vector name="origin" x="41" y="78"/><int name="z" value="0"/><string name="_hash" value="65391631c3cece0618b75ac5589000b8a06ff5b07390eb01c6e9a7b9bc8f7284"/></canvas><canvas name="5" width="84" height="81"><vector name="origin" x="41" y="78"/><int name="z" value="0"/><string name="_hash" value="99cfaaebc4d1a5a3917054160f3744b83550a213fb91a7d56199d5ee8df85960"/></canvas><canvas name="6" width="84" height="81"><vector name="origin" x="41" y="78"/><int name="z" value="0"/><string name="_hash" value="d41651e45a6f49b3e97303db5e99371786dfd66691ee4a6bf020820163b5951f"/></canvas><canvas name="7" width="84" height="81"><vector name="origin" x="41" y="78"/><int name="z" value="0"/><string name="_hash" value="a81dbfee2677c7f0a4859ec838def267ad538e4381e823b17ad5e035111a5b35"/></canvas></imgdir><imgdir name="move"><canvas name="0" width="84" height="81"><vector name="origin" x="41" y="78"/><int name="z" value="0"/><string name="_hash" value="f677453cc0b80536a0be9867bb11e3bcd7f1fc80fabee1a03e904487af40c6e9"/></canvas><canvas name="1" width="84" height="81"><vector name="origin" x="41" y="78"/><int name="z" value="0"/><string name="_hash" value="6b7e61a9efedd20c544fba31323fc79487f6d8a5c117c5e8ace921ad0edba7b3"/></canvas><canvas name="2" width="84" height="81"><vector name="origin" x="41" y="79"/><int name="z" value="0"/><string name="_hash" value="ed26cdb76e05e17595f4a7b591064985c3712527880accbbd7132d37a530070a"/></canvas><canvas name="3" width="85" height="81"><vector name="origin" x="41" y="79"/><int name="z" value="0"/><string name="_hash" value="d3ba8ec4a0da9e6aa27e8022e1506e98c5686b5ebdc1ec6f470d36aa1b9b80d3"/></canvas><canvas name="4" width="84" height="81"><vector name="origin" x="41" y="78"/><int name="z" value="0"/><string name="_hash" value="50a7a5ed82d4a5ac4c14a38116329e9262ef5aa9cefbab518ae47813042b780a"/></canvas><canvas name="5" width="84" height="81"><vector name="origin" x="41" y="78"/><int name="z" value="0"/><string name="_hash" value="b68e69e10ac56e68cc7a0d9078437782aeed6e2e528515ada607e7eff43dbbf6"/></canvas><canvas name="6" width="84" height="81"><vector name="origin" x="41" y="79"/><int name="z" value="0"/><string name="_hash" value="9831133429d5f6bdc9945be99506370c1e8bc47165dee81357f7d366769b90d8"/></canvas><canvas name="7" width="85" height="81"><vector name="origin" x="41" y="79"/><int name="z" value="0"/><string name="_hash" value="d43d987b051b3916b742e3b9a2e5f2cf6cc8aac0a0366b6915e0275dd34b92b9"/></canvas><canvas name="8" width="1" height="1"><vector name="origin" x="41" y="78"/><int name="z" value="0"/><string name="_inlink" value="move/0"/></canvas><canvas name="9" width="84" height="81"><vector name="origin" x="41" y="78"/><int name="z" value="0"/><string name="_hash" value="3d28d6168170fd2c67d2beefe32941ba24f773781ce257a62e5c3f9980bd7957"/></canvas><canvas name="10" width="84" height="81"><vector name="origin" x="41" y="79"/><int name="z" value="0"/><string name="_hash" value="dd4cad2653560bdbf8dcb6f36526ae40768a0fcb85acd05269ba2fa6ea64c387"/></canvas><canvas name="11" width="85" height="81"><vector name="origin" x="41" y="79"/><int name="z" value="0"/><string name="_hash" value="081c96d678d19abb26803373b7979c61a2f585bca4ee9928550dfc36d685a7f9"/></canvas><canvas name="12" width="1" height="1"><vector name="origin" x="41" y="78"/><int name="z" value="0"/><string name="_inlink" value="move/4"/></canvas><canvas name="13" width="1" height="1"><vector name="origin" x="41" y="78"/><int name="z" value="0"/><string name="_inlink" value="move/5"/></canvas><canvas name="14" width="1" height="1"><vector name="origin" x="41" y="79"/><int name="z" value="0"/><string name="_inlink" value="move/6"/></canvas><canvas name="15" width="85" height="81"><vector name="origin" x="41" y="79"/><int name="z" value="0"/><string name="_hash" value="b62c44a4c91b35889503552aa691d2ec50783f2488205cab03d5e41a6347d9c8"/></canvas></imgdir><imgdir name="condition1"><imgdir name="stand"><canvas name="0" width="1" height="1"><vector name="origin" x="41" y="78"/><int name="z" value="0"/><string name="_inlink" value="stand/0"/></canvas><canvas name="1" width="1" height="1"><vector name="origin" x="41" y="78"/><int name="z" value="0"/><string name="_inlink" value="stand/1"/></canvas><canvas name="2" width="1" height="1"><vector name="origin" x="41" y="78"/><int name="z" value="0"/><string name="_inlink" value="stand/2"/></canvas><canvas name="3" width="1" height="1"><vector name="origin" x="41" y="78"/><int name="z" value="0"/><string name="_inlink" value="stand/3"/></canvas><canvas name="4" width="1" height="1"><vector name="origin" x="41" y="78"/><int name="z" value="0"/><string name="_inlink" value="stand/4"/></canvas><canvas name="5" width="1" height="1"><vector name="origin" x="41" y="78"/><int name="z" value="0"/><string name="_inlink" value="stand/5"/></canvas><canvas name="6" width="1" height="1"><vector name="origin" x="41" y="78"/><int name="z" value="0"/><string name="_inlink" value="stand/6"/></canvas><canvas name="7" width="1" height="1"><vector name="origin" x="41" y="78"/><int name="z" value="0"/><string name="_inlink" value="stand/7"/></canvas></imgdir><imgdir name="say"><canvas name="0" width="1" height="1"><vector name="origin" x="41" y="78"/><int name="z" value="0"/><string name="_inlink" value="say/0"/></canvas><canvas name="1" width="1" height="1"><vector name="origin" x="41" y="78"/><int name="z" value="0"/><string name="_inlink" value="say/1"/></canvas><canvas name="2" width="1" height="1"><vector name="origin" x="41" y="78"/><int name="z" value="0"/><string name="_inlink" value="say/2"/></canvas><canvas name="3" width="1" height="1"><vector name="origin" x="41" y="78"/><int name="z" value="0"/><string name="_inlink" value="say/3"/></canvas><canvas name="4" width="1" height="1"><vector name="origin" x="41" y="78"/><int name="z" value="0"/><string name="_inlink" value="say/4"/></canvas><canvas name="5" width="1" height="1"><vector name="origin" x="41" y="78"/><int name="z" value="0"/><string name="_inlink" value="say/5"/></canvas><canvas name="6" width="1" height="1"><vector name="origin" x="41" y="78"/><int name="z" value="0"/><string name="_inlink" value="say/6"/></canvas><canvas name="7" width="1" height="1"><vector name="origin" x="41" y="78"/><int name="z" value="0"/><string name="_inlink" value="say/7"/></canvas></imgdir><imgdir name="move"><canvas name="0" width="1" height="1"><vector name="origin" x="41" y="78"/><int name="z" value="0"/><string name="_inlink" value="move/0"/></canvas><canvas name="1" width="1" height="1"><vector name="origin" x="41" y="78"/><int name="z" value="0"/><string name="_inlink" value="move/1"/></canvas><canvas name="2" width="1" height="1"><vector name="origin" x="41" y="79"/><int name="z" value="0"/><string name="_inlink" value="move/2"/></canvas><canvas name="3" width="1" height="1"><vector name="origin" x="41" y="79"/><int name="z" value="0"/><string name="_inlink" value="move/3"/></canvas><canvas name="4" width="1" height="1"><vector name="origin" x="41" y="78"/><int name="z" value="0"/><string name="_inlink" value="move/4"/></canvas><canvas name="5" width="1" height="1"><vector name="origin" x="41" y="78"/><int name="z" value="0"/><string name="_inlink" value="move/5"/></canvas><canvas name="6" width="1" height="1"><vector name="origin" x="41" y="79"/><int name="z" value="0"/><string name="_inlink" value="move/6"/></canvas><canvas name="7" width="1" height="1"><vector name="origin" x="41" y="79"/><int name="z" value="0"/><string name="_inlink" value="move/7"/></canvas><canvas name="8" width="1" height="1"><vector name="origin" x="41" y="78"/><int name="z" value="0"/><string name="_inlink" value="move/0"/></canvas><canvas name="9" width="1" height="1"><vector name="origin" x="41" y="78"/><int name="z" value="0"/><string name="_inlink" value="move/9"/></canvas><canvas name="10" width="1" height="1"><vector name="origin" x="41" y="79"/><int name="z" value="0"/><string name="_inlink" value="move/10"/></canvas><canvas name="11" width="1" height="1"><vector name="origin" x="41" y="79"/><int name="z" value="0"/><string name="_inlink" value="move/11"/></canvas><canvas name="12" width="1" height="1"><vector name="origin" x="41" y="78"/><int name="z" value="0"/><string name="_inlink" value="move/4"/></canvas><canvas name="13" width="1" height="1"><vector name="origin" x="41" y="78"/><int name="z" value="0"/><string name="_inlink" value="move/5"/></canvas><canvas name="14" width="1" height="1"><vector name="origin" x="41" y="79"/><int name="z" value="0"/><string name="_inlink" value="move/6"/></canvas><canvas name="15" width="1" height="1"><vector name="origin" x="41" y="79"/><int name="z" value="0"/><string name="_inlink" value="move/15"/></canvas></imgdir><int name="61292" value="2"/><int name="61317" value="2"/><int name="hide" value="1"/></imgdir><imgdir name="condition2"><imgdir name="stand"><canvas name="0" width="1" height="1"><vector name="origin" x="41" y="78"/><int name="z" value="0"/><string name="_inlink" value="stand/0"/></canvas><canvas name="1" width="1" height="1"><vector name="origin" x="41" y="78"/><int name="z" value="0"/><string name="_inlink" value="stand/1"/></canvas><canvas name="2" width="1" height="1"><vector name="origin" x="41" y="78"/><int name="z" value="0"/><string name="_inlink" value="stand/2"/></canvas><canvas name="3" width="1" height="1"><vector name="origin" x="41" y="78"/><int name="z" value="0"/><string name="_inlink" value="stand/3"/></canvas><canvas name="4" width="1" height="1"><vector name="origin" x="41" y="78"/><int name="z" value="0"/><string name="_inlink" value="stand/4"/></canvas><canvas name="5" width="1" height="1"><vector name="origin" x="41" y="78"/><int name="z" value="0"/><string name="_inlink" value="stand/5"/></canvas><canvas name="6" width="1" height="1"><vector name="origin" x="41" y="78"/><int name="z" value="0"/><string name="_inlink" value="stand/6"/></canvas><canvas name="7" width="1" height="1"><vector name="origin" x="41" y="78"/><int name="z" value="0"/><string name="_inlink" value="stand/7"/></canvas></imgdir><imgdir name="say"><canvas name="0" width="1" height="1"><vector name="origin" x="41" y="78"/><int name="z" value="0"/><string name="_inlink" value="say/0"/></canvas><canvas name="1" width="1" height="1"><vector name="origin" x="41" y="78"/><int name="z" value="0"/><string name="_inlink" value="say/1"/></canvas><canvas name="2" width="1" height="1"><vector name="origin" x="41" y="78"/><int name="z" value="0"/><string name="_inlink" value="say/2"/></canvas><canvas name="3" width="1" height="1"><vector name="origin" x="41" y="78"/><int name="z" value="0"/><string name="_inlink" value="say/3"/></canvas><canvas name="4" width="1" height="1"><vector name="origin" x="41" y="78"/><int name="z" value="0"/><string name="_inlink" value="say/4"/></canvas><canvas name="5" width="1" height="1"><vector name="origin" x="41" y="78"/><int name="z" value="0"/><string name="_inlink" value="say/5"/></canvas><canvas name="6" width="1" height="1"><vector name="origin" x="41" y="78"/><int name="z" value="0"/><string name="_inlink" value="say/6"/></canvas><canvas name="7" width="1" height="1"><vector name="origin" x="41" y="78"/><int name="z" value="0"/><string name="_inlink" value="say/7"/></canvas></imgdir><imgdir name="move"><canvas name="0" width="1" height="1"><vector name="origin" x="41" y="78"/><int name="z" value="0"/><string name="_inlink" value="move/0"/></canvas><canvas name="1" width="1" height="1"><vector name="origin" x="41" y="78"/><int name="z" value="0"/><string name="_inlink" value="move/1"/></canvas><canvas name="2" width="1" height="1"><vector name="origin" x="41" y="79"/><int name="z" value="0"/><string name="_inlink" value="move/2"/></canvas><canvas name="3" width="1" height="1"><vector name="origin" x="41" y="79"/><int name="z" value="0"/><string name="_inlink" value="move/3"/></canvas><canvas name="4" width="1" height="1"><vector name="origin" x="41" y="78"/><int name="z" value="0"/><string name="_inlink" value="move/4"/></canvas><canvas name="5" width="1" height="1"><vector name="origin" x="41" y="78"/><int name="z" value="0"/><string name="_inlink" value="move/5"/></canvas><canvas name="6" width="1" height="1"><vector name="origin" x="41" y="79"/><int name="z" value="0"/><string name="_inlink" value="move/6"/></canvas><canvas name="7" width="1" height="1"><vector name="origin" x="41" y="79"/><int name="z" value="0"/><string name="_inlink" value="move/7"/></canvas><canvas name="8" width="1" height="1"><vector name="origin" x="41" y="78"/><int name="z" value="0"/><string name="_inlink" value="move/0"/></canvas><canvas name="9" width="1" height="1"><vector name="origin" x="41" y="78"/><int name="z" value="0"/><string name="_inlink" value="move/9"/></canvas><canvas name="10" width="1" height="1"><vector name="origin" x="41" y="79"/><int name="z" value="0"/><string name="_inlink" value="move/10"/></canvas><canvas name="11" width="1" height="1"><vector name="origin" x="41" y="79"/><int name="z" value="0"/><string name="_inlink" value="move/11"/></canvas><canvas name="12" width="1" height="1"><vector name="origin" x="41" y="78"/><int name="z" value="0"/><string name="_inlink" value="move/4"/></canvas><canvas name="13" width="1" height="1"><vector name="origin" x="41" y="78"/><int name="z" value="0"/><string name="_inlink" value="move/5"/></canvas><canvas name="14" width="1" height="1"><vector name="origin" x="41" y="79"/><int name="z" value="0"/><string name="_inlink" value="move/6"/></canvas><canvas name="15" width="1" height="1"><vector name="origin" x="41" y="79"/><int name="z" value="0"/><string name="_inlink" value="move/15"/></canvas></imgdir><int name="61292" value="2"/><int name="61317" value="1"/></imgdir><imgdir name="condition3"><imgdir name="stand"><canvas name="0" width="1" height="1"><vector name="origin" x="41" y="78"/><int name="z" value="0"/><string name="_inlink" value="stand/0"/></canvas><canvas name="1" width="1" height="1"><vector name="origin" x="41" y="78"/><int name="z" value="0"/><string name="_inlink" value="stand/1"/></canvas><canvas name="2" width="1" height="1"><vector name="origin" x="41" y="78"/><int name="z" value="0"/><string name="_inlink" value="stand/2"/></canvas><canvas name="3" width="1" height="1"><vector name="origin" x="41" y="78"/><int name="z" value="0"/><string name="_inlink" value="stand/3"/></canvas><canvas name="4" width="1" height="1"><vector name="origin" x="41" y="78"/><int name="z" value="0"/><string name="_inlink" value="stand/4"/></canvas><canvas name="5" width="1" height="1"><vector name="origin" x="41" y="78"/><int name="z" value="0"/><string name="_inlink" value="stand/5"/></canvas><canvas name="6" width="1" height="1"><vector name="origin" x="41" y="78"/><int name="z" value="0"/><string name="_inlink" value="stand/6"/></canvas><canvas name="7" width="1" height="1"><vector name="origin" x="41" y="78"/><int name="z" value="0"/><string name="_inlink" value="stand/7"/></canvas></imgdir><imgdir name="say"><canvas name="0" width="1" height="1"><vector name="origin" x="41" y="78"/><int name="z" value="0"/><string name="_inlink" value="say/0"/></canvas><canvas name="1" width="1" height="1"><vector name="origin" x="41" y="78"/><int name="z" value="0"/><string name="_inlink" value="say/1"/></canvas><canvas name="2" width="1" height="1"><vector name="origin" x="41" y="78"/><int name="z" value="0"/><string name="_inlink" value="say/2"/></canvas><canvas name="3" width="1" height="1"><vector name="origin" x="41" y="78"/><int name="z" value="0"/><string name="_inlink" value="say/3"/></canvas><canvas name="4" width="1" height="1"><vector name="origin" x="41" y="78"/><int name="z" value="0"/><string name="_inlink" value="say/4"/></canvas><canvas name="5" width="1" height="1"><vector name="origin" x="41" y="78"/><int name="z" value="0"/><string name="_inlink" value="say/5"/></canvas><canvas name="6" width="1" height="1"><vector name="origin" x="41" y="78"/><int name="z" value="0"/><string name="_inlink" value="say/6"/></canvas><canvas name="7" width="1" height="1"><vector name="origin" x="41" y="78"/><int name="z" value="0"/><string name="_inlink" value="say/7"/></canvas></imgdir><imgdir name="move"><canvas name="0" width="1" height="1"><vector name="origin" x="41" y="78"/><int name="z" value="0"/><string name="_inlink" value="move/0"/></canvas><canvas name="1" width="1" height="1"><vector name="origin" x="41" y="78"/><int name="z" value="0"/><string name="_inlink" value="move/1"/></canvas><canvas name="2" width="1" height="1"><vector name="origin" x="41" y="79"/><int name="z" value="0"/><string name="_inlink" value="move/2"/></canvas><canvas name="3" width="1" height="1"><vector name="origin" x="41" y="79"/><int name="z" value="0"/><string name="_inlink" value="move/3"/></canvas><canvas name="4" width="1" height="1"><vector name="origin" x="41" y="78"/><int name="z" value="0"/><string name="_inlink" value="move/4"/></canvas><canvas name="5" width="1" height="1"><vector name="origin" x="41" y="78"/><int name="z" value="0"/><string name="_inlink" value="move/5"/></canvas><canvas name="6" width="1" height="1"><vector name="origin" x="41" y="79"/><int name="z" value="0"/><string name="_inlink" value="move/6"/></canvas><canvas name="7" width="1" height="1"><vector name="origin" x="41" y="79"/><int name="z" value="0"/><string name="_inlink" value="move/7"/></canvas><canvas name="8" width="1" height="1"><vector name="origin" x="41" y="78"/><int name="z" value="0"/><string name="_inlink" value="move/0"/></canvas><canvas name="9" width="1" height="1"><vector name="origin" x="41" y="78"/><int name="z" value="0"/><string name="_inlink" value="move/9"/></canvas><canvas name="10" width="1" height="1"><vector name="origin" x="41" y="79"/><int name="z" value="0"/><string name="_inlink" value="move/10"/></canvas><canvas name="11" width="1" height="1"><vector name="origin" x="41" y="79"/><int name="z" value="0"/><string name="_inlink" value="move/11"/></canvas><canvas name="12" width="1" height="1"><vector name="origin" x="41" y="78"/><int name="z" value="0"/><string name="_inlink" value="move/4"/></canvas><canvas name="13" width="1" height="1"><vector name="origin" x="41" y="78"/><int name="z" value="0"/><string name="_inlink" value="move/5"/></canvas><canvas name="14" width="1" height="1"><vector name="origin" x="41" y="79"/><int name="z" value="0"/><string name="_inlink" value="move/6"/></canvas><canvas name="15" width="1" height="1"><vector name="origin" x="41" y="79"/><int name="z" value="0"/><string name="_inlink" value="move/15"/></canvas></imgdir><int name="61292" value="2"/><int name="61317" value="0"/></imgdir><imgdir name="condition4"><imgdir name="stand"><canvas name="0" width="1" height="1"><vector name="origin" x="41" y="78"/><int name="z" value="0"/><string name="_inlink" value="stand/0"/></canvas><canvas name="1" width="1" height="1"><vector name="origin" x="41" y="78"/><int name="z" value="0"/><string name="_inlink" value="stand/1"/></canvas><canvas name="2" width="1" height="1"><vector name="origin" x="41" y="78"/><int name="z" value="0"/><string name="_inlink" value="stand/2"/></canvas><canvas name="3" width="1" height="1"><vector name="origin" x="41" y="78"/><int name="z" value="0"/><string name="_inlink" value="stand/3"/></canvas><canvas name="4" width="1" height="1"><vector name="origin" x="41" y="78"/><int name="z" value="0"/><string name="_inlink" value="stand/4"/></canvas><canvas name="5" width="1" height="1"><vector name="origin" x="41" y="78"/><int name="z" value="0"/><string name="_inlink" value="stand/5"/></canvas><canvas name="6" width="1" height="1"><vector name="origin" x="41" y="78"/><int name="z" value="0"/><string name="_inlink" value="stand/6"/></canvas><canvas name="7" width="1" height="1"><vector name="origin" x="41" y="78"/><int name="z" value="0"/><string name="_inlink" value="stand/7"/></canvas></imgdir><imgdir name="say"><canvas name="0" width="1" height="1"><vector name="origin" x="41" y="78"/><int name="z" value="0"/><string name="_inlink" value="say/0"/></canvas><canvas name="1" width="1" height="1"><vector name="origin" x="41" y="78"/><int name="z" value="0"/><string name="_inlink" value="say/1"/></canvas><canvas name="2" width="1" height="1"><vector name="origin" x="41" y="78"/><int name="z" value="0"/><string name="_inlink" value="say/2"/></canvas><canvas name="3" width="1" height="1"><vector name="origin" x="41" y="78"/><int name="z" value="0"/><string name="_inlink" value="say/3"/></canvas><canvas name="4" width="1" height="1"><vector name="origin" x="41" y="78"/><int name="z" value="0"/><string name="_inlink" value="say/4"/></canvas><canvas name="5" width="1" height="1"><vector name="origin" x="41" y="78"/><int name="z" value="0"/><string name="_inlink" value="say/5"/></canvas><canvas name="6" width="1" height="1"><vector name="origin" x="41" y="78"/><int name="z" value="0"/><string name="_inlink" value="say/6"/></canvas><canvas name="7" width="1" height="1"><vector name="origin" x="41" y="78"/><int name="z" value="0"/><string name="_inlink" value="say/7"/></canvas></imgdir><imgdir name="move"><canvas name="0" width="1" height="1"><vector name="origin" x="41" y="78"/><int name="z" value="0"/><string name="_inlink" value="move/0"/></canvas><canvas name="1" width="1" height="1"><vector name="origin" x="41" y="78"/><int name="z" value="0"/><string name="_inlink" value="move/1"/></canvas><canvas name="2" width="1" height="1"><vector name="origin" x="41" y="79"/><int name="z" value="0"/><string name="_inlink" value="move/2"/></canvas><canvas name="3" width="1" height="1"><vector name="origin" x="41" y="79"/><int name="z" value="0"/><string name="_inlink" value="move/3"/></canvas><canvas name="4" width="1" height="1"><vector name="origin" x="41" y="78"/><int name="z" value="0"/><string name="_inlink" value="move/4"/></canvas><canvas name="5" width="1" height="1"><vector name="origin" x="41" y="78"/><int name="z" value="0"/><string name="_inlink" value="move/5"/></canvas><canvas name="6" width="1" height="1"><vector name="origin" x="41" y="79"/><int name="z" value="0"/><string name="_inlink" value="move/6"/></canvas><canvas name="7" width="1" height="1"><vector name="origin" x="41" y="79"/><int name="z" value="0"/><string name="_inlink" value="move/7"/></canvas><canvas name="8" width="1" height="1"><vector name="origin" x="41" y="78"/><int name="z" value="0"/><string name="_inlink" value="move/0"/></canvas><canvas name="9" width="1" height="1"><vector name="origin" x="41" y="78"/><int name="z" value="0"/><string name="_inlink" value="move/9"/></canvas><canvas name="10" width="1" height="1"><vector name="origin" x="41" y="79"/><int name="z" value="0"/><string name="_inlink" value="move/10"/></canvas><canvas name="11" width="1" height="1"><vector name="origin" x="41" y="79"/><int name="z" value="0"/><string name="_inlink" value="move/11"/></canvas><canvas name="12" width="1" height="1"><vector name="origin" x="41" y="78"/><int name="z" value="0"/><string name="_inlink" value="move/4"/></canvas><canvas name="13" width="1" height="1"><vector name="origin" x="41" y="78"/><int name="z" value="0"/><string name="_inlink" value="move/5"/></canvas><canvas name="14" width="1" height="1"><vector name="origin" x="41" y="79"/><int name="z" value="0"/><string name="_inlink" value="move/6"/></canvas><canvas name="15" width="1" height="1"><vector name="origin" x="41" y="79"/><int name="z" value="0"/><string name="_inlink" value="move/15"/></canvas></imgdir><int name="61292" value="2"/><int name="61278" value="1"/></imgdir><imgdir name="condition5"><imgdir name="stand"><canvas name="0" width="75" height="83"><vector name="origin" x="38" y="83"/><int name="z" value="0"/><string name="_hash" value="de5442b84ef74d4abffef9ee71339de2dfdb1ed76cdf7eabe8e0243c22e7096f"/></canvas><canvas name="1" width="75" height="83"><vector name="origin" x="38" y="83"/><int name="z" value="0"/><string name="_hash" value="1b6790f39362bdde20dce45a2ee0bdf707369b4bd2a45aa65d1bf04e75f69605"/></canvas><canvas name="2" width="75" height="83"><vector name="origin" x="38" y="83"/><int name="z" value="0"/><string name="_hash" value="dab16735cc6f38d9f9a2e1be00f4202addeda82503fd1f39cfc1ceb0eaca2495"/></canvas><canvas name="3" width="75" height="83"><vector name="origin" x="38" y="83"/><int name="z" value="0"/><string name="_hash" value="9720b52ddac644adbfa908ac9a89012b12a0bf82184550bc0b74c408ec1ce4f1"/></canvas><canvas name="4" width="75" height="83"><vector name="origin" x="38" y="83"/><int name="z" value="0"/><string name="_hash" value="9ced692d7b2c9f896e62b9d7b3df8977a10eeb67eff4b12aae014ebe5f1d600b"/></canvas><canvas name="5" width="75" height="83"><vector name="origin" x="38" y="83"/><int name="z" value="0"/><string name="_hash" value="3b6904e7f428368c014d9ffe9c4efde51fd1f2ed4a6c071fe8343264d58033f3"/></canvas><canvas name="6" width="75" height="83"><vector name="origin" x="38" y="83"/><int name="z" value="0"/><string name="_hash" value="9b1e9368526bf0a8af4757b9586ea13c6d2618bdda657a9910ee1e8ee220004c"/></canvas><canvas name="7" width="75" height="83"><vector name="origin" x="38" y="83"/><int name="z" value="0"/><string name="_hash" value="17b25190ded11283af74dbed002ac71165aed50b03e75d2fe554d14ee91aa08c"/></canvas></imgdir><imgdir name="say"><canvas name="0" width="75" height="83"><vector name="origin" x="38" y="83"/><int name="z" value="0"/><string name="_hash" value="099918bd246ac02e918c05e3e6ebf01937a1f94a8eb8f44407bb530c5bb6c491"/></canvas><canvas name="1" width="75" height="83"><vector name="origin" x="38" y="83"/><int name="z" value="0"/><string name="_hash" value="fffca33a7af8908c3c8d49eab9d61945438858457fe051e7609f6edd2d5ec8ae"/></canvas><canvas name="2" width="75" height="83"><vector name="origin" x="38" y="83"/><int name="z" value="0"/><string name="_hash" value="c9150a6fe3631048ef0826498e3d33d13d9a7ba896aedd4c0f39ffc57014ab23"/></canvas><canvas name="3" width="75" height="83"><vector name="origin" x="38" y="83"/><int name="z" value="0"/><string name="_hash" value="294abaa3db87e2df44bfefa3a7c906c2df629d9ebab260dbc8ab167d0dd1bcee"/></canvas><canvas name="4" width="75" height="83"><vector name="origin" x="38" y="83"/><int name="z" value="0"/><string name="_hash" value="d727a569858d1b0db1b9a1fd1be24c47a09a78e230810da75cd7f6abb15283f8"/></canvas><canvas name="5" width="75" height="83"><vector name="origin" x="38" y="83"/><int name="z" value="0"/><string name="_hash" value="a953c16752541e7a2904d2c26ba23461ca852f06060cf6e90c1851562507ddf9"/></canvas><canvas name="6" width="75" height="83"><vector name="origin" x="38" y="83"/><int name="z" value="0"/><string name="_hash" value="a0abc20af310d66bdc2eb39dcfca14a9ac603b5f1adebcc71fad32aa0e861266"/></canvas><canvas name="7" width="75" height="83"><vector name="origin" x="38" y="83"/><int name="z" value="0"/><string name="_hash" value="29c1854e678d34c22e946ee3e051c838ec1ae95a8f32d0aacddedcb64a3166dd"/></canvas></imgdir><imgdir name="move"><canvas name="0" width="76" height="82"><vector name="origin" x="39" y="82"/><int name="z" value="0"/><string name="_hash" value="4650086625d2b3dc34e09b61a1176d9408e7bb53f7bb89b24e62a780a924b213"/></canvas><canvas name="1" width="77" height="82"><vector name="origin" x="39" y="82"/><int name="z" value="0"/><string name="_hash" value="73b09709d8716ea260a5bd76c5b7d12f667e3e1517f5bee083b974052182c59c"/></canvas><canvas name="2" width="75" height="82"><vector name="origin" x="38" y="83"/><int name="z" value="0"/><string name="_hash" value="3824f619ffef20c329e8b570e7638fcf24660484107de7c26a6f2e910579aee9"/></canvas><canvas name="3" width="76" height="83"><vector name="origin" x="39" y="83"/><int name="z" value="0"/><string name="_hash" value="238d02862faaad05963178909865810e83d1efe014b8a915f87467a502569245"/></canvas><canvas name="4" width="76" height="82"><vector name="origin" x="39" y="82"/><int name="z" value="0"/><string name="_hash" value="41b6856c53922075e23798eb72f98206c1c8eabe09c8e0fd1faf243ad2e3f01c"/></canvas><canvas name="5" width="77" height="82"><vector name="origin" x="39" y="82"/><int name="z" value="0"/><string name="_hash" value="6f6d79cae9a4c7f35c36e9e3ff0865d1fe44c60e9bff437fb99e60880d54939e"/></canvas><canvas name="6" width="75" height="83"><vector name="origin" x="38" y="83"/><int name="z" value="0"/><string name="_hash" value="fa555584feb311850e966660debbfb0bb64d3bdac5e460b93ba6fe5ebef5aa9e"/></canvas><canvas name="7" width="76" height="83"><vector name="origin" x="39" y="83"/><int name="z" value="0"/><string name="_hash" value="07c91f5939278e8886ec8cf8fcabada9760e035d9bb4c90cd329d5841a502f51"/></canvas><canvas name="8" width="1" height="1"><vector name="origin" x="39" y="82"/><int name="z" value="0"/><string name="_inlink" value="condition5/move/0"/></canvas><canvas name="9" width="77" height="82"><vector name="origin" x="39" y="82"/><int name="z" value="0"/><string name="_hash" value="48ff3c94dd2d781e5e6cfa67dfd27aa7cec8b05ae5cb494eed94c86e6d738524"/></canvas><canvas name="10" width="75" height="82"><vector name="origin" x="38" y="83"/><int name="z" value="0"/><string name="_hash" value="acb415950d97b2648a8498aea63c9bfeba398a749cf2d0868878e62b31ca23bf"/></canvas><canvas name="11" width="76" height="83"><vector name="origin" x="39" y="83"/><int name="z" value="0"/><string name="_hash" value="aaa687a9c580bd6a2cd096bf822bcac911a86a2d104e23fd7b48688ef3e49833"/></canvas><canvas name="12" width="1" height="1"><vector name="origin" x="39" y="82"/><int name="z" value="0"/><string name="_inlink" value="condition5/move/4"/></canvas><canvas name="13" width="1" height="1"><vector name="origin" x="39" y="82"/><int name="z" value="0"/><string name="_inlink" value="condition5/move/5"/></canvas><canvas name="14" width="75" height="83"><vector name="origin" x="38" y="83"/><int name="z" value="0"/><string name="_hash" value="2447dd016905122bde6c10d9859e8d9f4c26ed230272574efd9802487f3f648f"/></canvas><canvas name="15" width="76" height="83"><vector name="origin" x="39" y="83"/><int name="z" value="0"/><string name="_hash" value="c60b39a43d25d5fcf76cd4be5cc659536677def856f186da29e2761213263fa0"/></canvas></imgdir><int name="61293" value="2"/><int name="61317" value="2"/><int name="hide" value="1"/></imgdir><imgdir name="condition6"><imgdir name="stand"><canvas name="0" width="1" height="1"><vector name="origin" x="38" y="83"/><int name="z" value="0"/><string name="_inlink" value="condition5/stand/0"/></canvas><canvas name="1" width="1" height="1"><vector name="origin" x="38" y="83"/><int name="z" value="0"/><string name="_inlink" value="condition5/stand/1"/></canvas><canvas name="2" width="1" height="1"><vector name="origin" x="38" y="83"/><int name="z" value="0"/><string name="_inlink" value="condition5/stand/2"/></canvas><canvas name="3" width="1" height="1"><vector name="origin" x="38" y="83"/><int name="z" value="0"/><string name="_inlink" value="condition5/stand/3"/></canvas><canvas name="4" width="1" height="1"><vector name="origin" x="38" y="83"/><int name="z" value="0"/><string name="_inlink" value="condition5/stand/4"/></canvas><canvas name="5" width="1" height="1"><vector name="origin" x="38" y="83"/><int name="z" value="0"/><string name="_inlink" value="condition5/stand/5"/></canvas><canvas name="6" width="1" height="1"><vector name="origin" x="38" y="83"/><int name="z" value="0"/><string name="_inlink" value="condition5/stand/6"/></canvas><canvas name="7" width="1" height="1"><vector name="origin" x="38" y="83"/><int name="z" value="0"/><string name="_inlink" value="condition5/stand/7"/></canvas></imgdir><imgdir name="say"><canvas name="0" width="1" height="1"><vector name="origin" x="38" y="83"/><int name="z" value="0"/><string name="_inlink" value="condition5/say/0"/></canvas><canvas name="1" width="1" height="1"><vector name="origin" x="38" y="83"/><int name="z" value="0"/><string name="_inlink" value="condition5/say/1"/></canvas><canvas name="2" width="1" height="1"><vector name="origin" x="38" y="83"/><int name="z" value="0"/><string name="_inlink" value="condition5/say/2"/></canvas><canvas name="3" width="1" height="1"><vector name="origin" x="38" y="83"/><int name="z" value="0"/><string name="_inlink" value="condition5/say/3"/></canvas><canvas name="4" width="1" height="1"><vector name="origin" x="38" y="83"/><int name="z" value="0"/><string name="_inlink" value="condition5/say/4"/></canvas><canvas name="5" width="1" height="1"><vector name="origin" x="38" y="83"/><int name="z" value="0"/><string name="_inlink" value="condition5/say/5"/></canvas><canvas name="6" width="1" height="1"><vector name="origin" x="38" y="83"/><int name="z" value="0"/><string name="_inlink" value="condition5/say/6"/></canvas><canvas name="7" width="1" height="1"><vector name="origin" x="38" y="83"/><int name="z" value="0"/><string name="_inlink" value="condition5/say/7"/></canvas></imgdir><imgdir name="move"><canvas name="0" width="1" height="1"><vector name="origin" x="39" y="82"/><int name="z" value="0"/><string name="_inlink" value="condition5/move/0"/></canvas><canvas name="1" width="1" height="1"><vector name="origin" x="39" y="82"/><int name="z" value="0"/><string name="_inlink" value="condition5/move/1"/></canvas><canvas name="2" width="1" height="1"><vector name="origin" x="38" y="83"/><int name="z" value="0"/><string name="_inlink" value="condition5/move/2"/></canvas><canvas name="3" width="1" height="1"><vector name="origin" x="39" y="83"/><int name="z" value="0"/><string name="_inlink" value="condition5/move/3"/></canvas><canvas name="4" width="1" height="1"><vector name="origin" x="39" y="82"/><int name="z" value="0"/><string name="_inlink" value="condition5/move/4"/></canvas><canvas name="5" width="1" height="1"><vector name="origin" x="39" y="82"/><int name="z" value="0"/><string name="_inlink" value="condition5/move/5"/></canvas><canvas name="6" width="1" height="1"><vector name="origin" x="38" y="83"/><int name="z" value="0"/><string name="_inlink" value="condition5/move/6"/></canvas><canvas name="7" width="1" height="1"><vector name="origin" x="39" y="83"/><int name="z" value="0"/><string name="_inlink" value="condition5/move/7"/></canvas><canvas name="8" width="1" height="1"><vector name="origin" x="39" y="82"/><int name="z" value="0"/><string name="_inlink" value="condition5/move/0"/></canvas><canvas name="9" width="1" height="1"><vector name="origin" x="39" y="82"/><int name="z" value="0"/><string name="_inlink" value="condition5/move/9"/></canvas><canvas name="10" width="1" height="1"><vector name="origin" x="38" y="83"/><int name="z" value="0"/><string name="_inlink" value="condition5/move/10"/></canvas><canvas name="11" width="1" height="1"><vector name="origin" x="39" y="83"/><int name="z" value="0"/><string name="_inlink" value="condition5/move/11"/></canvas><canvas name="12" width="1" height="1"><vector name="origin" x="39" y="82"/><int name="z" value="0"/><string name="_inlink" value="condition5/move/4"/></canvas><canvas name="13" width="1" height="1"><vector name="origin" x="39" y="82"/><int name="z" value="0"/><string name="_inlink" value="condition5/move/5"/></canvas><canvas name="14" width="1" height="1"><vector name="origin" x="38" y="83"/><int name="z" value="0"/><string name="_inlink" value="condition5/move/14"/></canvas><canvas name="15" width="1" height="1"><vector name="origin" x="39" y="83"/><int name="z" value="0"/><string name="_inlink" value="condition5/move/15"/></canvas></imgdir><int name="61293" value="2"/><int name="61317" value="1"/></imgdir><imgdir name="condition7"><imgdir name="stand"><canvas name="0" width="1" height="1"><vector name="origin" x="38" y="83"/><int name="z" value="0"/><string name="_inlink" value="condition5/stand/0"/></canvas><canvas name="1" width="1" height="1"><vector name="origin" x="38" y="83"/><int name="z" value="0"/><string name="_inlink" value="condition5/stand/1"/></canvas><canvas name="2" width="1" height="1"><vector name="origin" x="38" y="83"/><int name="z" value="0"/><string name="_inlink" value="condition5/stand/2"/></canvas><canvas name="3" width="1" height="1"><vector name="origin" x="38" y="83"/><int name="z" value="0"/><string name="_inlink" value="condition5/stand/3"/></canvas><canvas name="4" width="1" height="1"><vector name="origin" x="38" y="83"/><int name="z" value="0"/><string name="_inlink" value="condition5/stand/4"/></canvas><canvas name="5" width="1" height="1"><vector name="origin" x="38" y="83"/><int name="z" value="0"/><string name="_inlink" value="condition5/stand/5"/></canvas><canvas name="6" width="1" height="1"><vector name="origin" x="38" y="83"/><int name="z" value="0"/><string name="_inlink" value="condition5/stand/6"/></canvas><canvas name="7" width="1" height="1"><vector name="origin" x="38" y="83"/><int name="z" value="0"/><string name="_inlink" value="condition5/stand/7"/></canvas></imgdir><imgdir name="say"><canvas name="0" width="1" height="1"><vector name="origin" x="38" y="83"/><int name="z" value="0"/><string name="_inlink" value="condition5/say/0"/></canvas><canvas name="1" width="1" height="1"><vector name="origin" x="38" y="83"/><int name="z" value="0"/><string name="_inlink" value="condition5/say/1"/></canvas><canvas name="2" width="1" height="1"><vector name="origin" x="38" y="83"/><int name="z" value="0"/><string name="_inlink" value="condition5/say/2"/></canvas><canvas name="3" width="1" height="1"><vector name="origin" x="38" y="83"/><int name="z" value="0"/><string name="_inlink" value="condition5/say/3"/></canvas><canvas name="4" width="1" height="1"><vector name="origin" x="38" y="83"/><int name="z" value="0"/><string name="_inlink" value="condition5/say/4"/></canvas><canvas name="5" width="1" height="1"><vector name="origin" x="38" y="83"/><int name="z" value="0"/><string name="_inlink" value="condition5/say/5"/></canvas><canvas name="6" width="1" height="1"><vector name="origin" x="38" y="83"/><int name="z" value="0"/><string name="_inlink" value="condition5/say/6"/></canvas><canvas name="7" width="1" height="1"><vector name="origin" x="38" y="83"/><int name="z" value="0"/><string name="_inlink" value="condition5/say/7"/></canvas></imgdir><imgdir name="move"><canvas name="0" width="1" height="1"><vector name="origin" x="39" y="82"/><int name="z" value="0"/><string name="_inlink" value="condition5/move/0"/></canvas><canvas name="1" width="1" height="1"><vector name="origin" x="39" y="82"/><int name="z" value="0"/><string name="_inlink" value="condition5/move/1"/></canvas><canvas name="2" width="1" height="1"><vector name="origin" x="38" y="83"/><int name="z" value="0"/><string name="_inlink" value="condition5/move/2"/></canvas><canvas name="3" width="1" height="1"><vector name="origin" x="39" y="83"/><int name="z" value="0"/><string name="_inlink" value="condition5/move/3"/></canvas><canvas name="4" width="1" height="1"><vector name="origin" x="39" y="82"/><int name="z" value="0"/><string name="_inlink" value="condition5/move/4"/></canvas><canvas name="5" width="1" height="1"><vector name="origin" x="39" y="82"/><int name="z" value="0"/><string name="_inlink" value="condition5/move/5"/></canvas><canvas name="6" width="1" height="1"><vector name="origin" x="38" y="83"/><int name="z" value="0"/><string name="_inlink" value="condition5/move/6"/></canvas><canvas name="7" width="1" height="1"><vector name="origin" x="39" y="83"/><int name="z" value="0"/><string name="_inlink" value="condition5/move/7"/></canvas><canvas name="8" width="1" height="1"><vector name="origin" x="39" y="82"/><int name="z" value="0"/><string name="_inlink" value="condition5/move/0"/></canvas><canvas name="9" width="1" height="1"><vector name="origin" x="39" y="82"/><int name="z" value="0"/><string name="_inlink" value="condition5/move/9"/></canvas><canvas name="10" width="1" height="1"><vector name="origin" x="38" y="83"/><int name="z" value="0"/><string name="_inlink" value="condition5/move/10"/></canvas><canvas name="11" width="1" height="1"><vector name="origin" x="39" y="83"/><int name="z" value="0"/><string name="_inlink" value="condition5/move/11"/></canvas><canvas name="12" width="1" height="1"><vector name="origin" x="39" y="82"/><int name="z" value="0"/><string name="_inlink" value="condition5/move/4"/></canvas><canvas name="13" width="1" height="1"><vector name="origin" x="39" y="82"/><int name="z" value="0"/><string name="_inlink" value="condition5/move/5"/></canvas><canvas name="14" width="1" height="1"><vector name="origin" x="38" y="83"/><int name="z" value="0"/><string name="_inlink" value="condition5/move/14"/></canvas><canvas name="15" width="1" height="1"><vector name="origin" x="39" y="83"/><int name="z" value="0"/><string name="_inlink" value="condition5/move/15"/></canvas></imgdir><int name="61293" value="2"/><int name="61317" value="0"/></imgdir><imgdir name="condition8"><imgdir name="stand"><canvas name="0" width="1" height="1"><vector name="origin" x="38" y="83"/><int name="z" value="0"/><string name="_inlink" value="condition5/stand/0"/></canvas><canvas name="1" width="1" height="1"><vector name="origin" x="38" y="83"/><int name="z" value="0"/><string name="_inlink" value="condition5/stand/1"/></canvas><canvas name="2" width="1" height="1"><vector name="origin" x="38" y="83"/><int name="z" value="0"/><string name="_inlink" value="condition5/stand/2"/></canvas><canvas name="3" width="1" height="1"><vector name="origin" x="38" y="83"/><int name="z" value="0"/><string name="_inlink" value="condition5/stand/3"/></canvas><canvas name="4" width="1" height="1"><vector name="origin" x="38" y="83"/><int name="z" value="0"/><string name="_inlink" value="condition5/stand/4"/></canvas><canvas name="5" width="1" height="1"><vector name="origin" x="38" y="83"/><int name="z" value="0"/><string name="_inlink" value="condition5/stand/5"/></canvas><canvas name="6" width="1" height="1"><vector name="origin" x="38" y="83"/><int name="z" value="0"/><string name="_inlink" value="condition5/stand/6"/></canvas><canvas name="7" width="1" height="1"><vector name="origin" x="38" y="83"/><int name="z" value="0"/><string name="_inlink" value="condition5/stand/7"/></canvas></imgdir><imgdir name="say"><canvas name="0" width="1" height="1"><vector name="origin" x="38" y="83"/><int name="z" value="0"/><string name="_inlink" value="condition5/say/0"/></canvas><canvas name="1" width="1" height="1"><vector name="origin" x="38" y="83"/><int name="z" value="0"/><string name="_inlink" value="condition5/say/1"/></canvas><canvas name="2" width="1" height="1"><vector name="origin" x="38" y="83"/><int name="z" value="0"/><string name="_inlink" value="condition5/say/2"/></canvas><canvas name="3" width="1" height="1"><vector name="origin" x="38" y="83"/><int name="z" value="0"/><string name="_inlink" value="condition5/say/3"/></canvas><canvas name="4" width="1" height="1"><vector name="origin" x="38" y="83"/><int name="z" value="0"/><string name="_inlink" value="condition5/say/4"/></canvas><canvas name="5" width="1" height="1"><vector name="origin" x="38" y="83"/><int name="z" value="0"/><string name="_inlink" value="condition5/say/5"/></canvas><canvas name="6" width="1" height="1"><vector name="origin" x="38" y="83"/><int name="z" value="0"/><string name="_inlink" value="condition5/say/6"/></canvas><canvas name="7" width="1" height="1"><vector name="origin" x="38" y="83"/><int name="z" value="0"/><string name="_inlink" value="condition5/say/7"/></canvas></imgdir><imgdir name="move"><canvas name="0" width="1" height="1"><vector name="origin" x="39" y="82"/><int name="z" value="0"/><string name="_inlink" value="condition5/move/0"/></canvas><canvas name="1" width="1" height="1"><vector name="origin" x="39" y="82"/><int name="z" value="0"/><string name="_inlink" value="condition5/move/1"/></canvas><canvas name="2" width="1" height="1"><vector name="origin" x="38" y="83"/><int name="z" value="0"/><string name="_inlink" value="condition5/move/2"/></canvas><canvas name="3" width="1" height="1"><vector name="origin" x="39" y="83"/><int name="z" value="0"/><string name="_inlink" value="condition5/move/3"/></canvas><canvas name="4" width="1" height="1"><vector name="origin" x="39" y="82"/><int name="z" value="0"/><string name="_inlink" value="condition5/move/4"/></canvas><canvas name="5" width="1" height="1"><vector name="origin" x="39" y="82"/><int name="z" value="0"/><string name="_inlink" value="condition5/move/5"/></canvas><canvas name="6" width="1" height="1"><vector name="origin" x="38" y="83"/><int name="z" value="0"/><string name="_inlink" value="condition5/move/6"/></canvas><canvas name="7" width="1" height="1"><vector name="origin" x="39" y="83"/><int name="z" value="0"/><string name="_inlink" value="condition5/move/7"/></canvas><canvas name="8" width="1" height="1"><vector name="origin" x="39" y="82"/><int name="z" value="0"/><string name="_inlink" value="condition5/move/0"/></canvas><canvas name="9" width="1" height="1"><vector name="origin" x="39" y="82"/><int name="z" value="0"/><string name="_inlink" value="condition5/move/9"/></canvas><canvas name="10" width="1" height="1"><vector name="origin" x="38" y="83"/><int name="z" value="0"/><string name="_inlink" value="condition5/move/10"/></canvas><canvas name="11" width="1" height="1"><vector name="origin" x="39" y="83"/><int name="z" value="0"/><string name="_inlink" value="condition5/move/11"/></canvas><canvas name="12" width="1" height="1"><vector name="origin" x="39" y="82"/><int name="z" value="0"/><string name="_inlink" value="condition5/move/4"/></canvas><canvas name="13" width="1" height="1"><vector name="origin" x="39" y="82"/><int name="z" value="0"/><string name="_inlink" value="condition5/move/5"/></canvas><canvas name="14" width="1" height="1"><vector name="origin" x="38" y="83"/><int name="z" value="0"/><string name="_inlink" value="condition5/move/14"/></canvas><canvas name="15" width="1" height="1"><vector name="origin" x="39" y="83"/><int name="z" value="0"/><string name="_inlink" value="condition5/move/15"/></canvas></imgdir><int name="61293" value="2"/><int name="61278" value="1"/></imgdir></imgdir>