<?xml version="1.0" encoding="UTF-8" standalone="yes"?><imgdir name="9400593.img"><imgdir name="info"><int name="forceMove" value="1"/><canvas name="CaravanDialog" width="100" height="100"><vector name="origin" x="50" y="50"/><int name="z" value="0"/><string name="_hash" value="f38d8a8323a53cfd40e95199e08f212b0f2a2f0487da4be5f3465d039e2d4832"/></canvas><imgdir name="script"><imgdir name="0"><string name="script" value="SongOfHawar"/></imgdir></imgdir></imgdir><imgdir name="stand"><canvas name="0" width="54" height="68"><vector name="origin" x="24" y="67"/><int name="z" value="0"/><string name="_hash" value="f477bc1d4ecc0ca821cbfb4de2fe6e90bb523737e30e36b68d7f0b15127e5284"/></canvas><canvas name="1" width="54" height="68"><vector name="origin" x="24" y="67"/><int name="z" value="0"/><string name="_hash" value="6c74886bf0c5ae7bb5ccd67f3532cacdcbf9398f989fec3da33cb48434410069"/></canvas></imgdir><imgdir name="eye"><canvas name="0" width="54" height="68"><vector name="origin" x="24" y="67"/><int name="z" value="0"/><int name="delay" value="150"/><string name="_hash" value="28f4ca65a872a946671175da6fdef340290d5becbb5c3aaf1597b2ac5ce98586"/></canvas><canvas name="1" width="54" height="68"><vector name="origin" x="24" y="67"/><int name="z" value="0"/><int name="delay" value="150"/><string name="_hash" value="7d59413b5517f5cce6b0345697c1aa48bbf0fd596c2008f1dcedbbef438e6ecc"/></canvas><canvas name="2" width="54" height="68"><vector name="origin" x="24" y="67"/><int name="z" value="0"/><int name="delay" value="150"/><string name="_hash" value="cdede6e642ac0c8696f7ddbdc24a8ad7e782088a0d4ece84352aed48062de247"/></canvas><canvas name="3" width="54" height="68"><vector name="origin" x="24" y="67"/><int name="z" value="0"/><int name="delay" value="150"/><string name="_hash" value="4911b7c1091e15f6e3c69448a6cc6927097580480f3a52f77b21738ec3ae60f2"/></canvas><canvas name="4" width="54" height="68"><vector name="origin" x="24" y="67"/><int name="z" value="0"/><string name="_hash" value="8297b828283673e482695e49ece82906f57d744fd30232e6bbbd65ac1abd4e1c"/></canvas><canvas name="5" width="54" height="68"><vector name="origin" x="24" y="67"/><int name="z" value="0"/><string name="_hash" value="aa569659d6b4bcd3c7e5d0ed4561524df84a9dd3dc7fdc9047b3d7be19e7174f"/></canvas><canvas name="6" width="54" height="68"><vector name="origin" x="24" y="67"/><int name="z" value="0"/><string name="_hash" value="98f623193ff09b0f3f7c616507b0829127e6228b159d6a20b73e7e703039e66a"/></canvas><canvas name="7" width="54" height="68"><vector name="origin" x="24" y="67"/><int name="z" value="0"/><string name="_hash" value="3c8b1fdd985c816fb985c5cead0804a1f9da741fcdd0b03dfa18687377b96422"/></canvas></imgdir><imgdir name="say"><canvas name="0" width="54" height="68"><vector name="origin" x="24" y="67"/><int name="z" value="0"/><int name="delay" value="150"/><string name="_hash" value="34949d158cfcf17957a85607e7e7da1e495742bdb14aa57da0b43311b3faed66"/></canvas><canvas name="1" width="54" height="68"><vector name="origin" x="24" y="67"/><int name="z" value="0"/><int name="delay" value="150"/><string name="_hash" value="795311658eb7407cc24d3811c071b1a675fb000b605e83aea244a225f2113fff"/></canvas><canvas name="2" width="1" height="1"><vector name="origin" x="24" y="67"/><int name="z" value="0"/><int name="delay" value="150"/><string name="_inlink" value="say/0"/></canvas><canvas name="3" width="54" height="68"><vector name="origin" x="24" y="67"/><int name="z" value="0"/><int name="delay" value="150"/><string name="_hash" value="d895c6635069422cfb17268b19570e23846932575635259e46c21338a7959370"/></canvas><canvas name="4" width="1" height="1"><vector name="origin" x="24" y="67"/><int name="z" value="0"/><string name="_inlink" value="say/0"/></canvas><canvas name="5" width="1" height="1"><vector name="origin" x="24" y="67"/><int name="z" value="0"/><string name="_inlink" value="say/3"/></canvas><canvas name="6" width="1" height="1"><vector name="origin" x="24" y="67"/><int name="z" value="0"/><string name="_inlink" value="say/0"/></canvas><canvas name="7" width="54" height="68"><vector name="origin" x="24" y="67"/><int name="z" value="0"/><string name="_hash" value="5cfe0a6d520dd23b1253ffa3aecf8e5d31383ec89e5da25e40da81326abfcbc4"/></canvas></imgdir><imgdir name="move"><canvas name="0" width="54" height="68"><vector name="origin" x="24" y="68"/><int name="z" value="0"/><string name="_hash" value="700f1cf40997bf23516e94054b4eb3fe117869b27d0c0f79e048d96d80ab0c26"/></canvas><canvas name="1" width="54" height="68"><vector name="origin" x="24" y="67"/><int name="z" value="0"/><string name="_hash" value="8267f9c3a9d1c1d79ba959b77a2cb75c5923677bb53eacedbee7f33020c0e904"/></canvas><canvas name="2" width="54" height="69"><vector name="origin" x="24" y="68"/><int name="z" value="0"/><string name="_hash" value="f36bc81931ffba4caf67f85114b4ce70cc263832b9a0427d2a3511ac08c8dcad"/></canvas><canvas name="3" width="54" height="68"><vector name="origin" x="24" y="67"/><int name="z" value="0"/><string name="_hash" value="b8a39ec3fd4556870abbdd66aee3d3d5c9657ebfdd63727e1d60efa0ec02efa6"/></canvas><int name="special" value="1"/></imgdir><imgdir name="condition"><imgdir name="64166"><string name="value" value="happy"/></imgdir><imgdir name="stand"><canvas name="0" width="54" height="68"><vector name="origin" x="24" y="67"/><int name="z" value="0"/><int name="delay" value="300"/><string name="_hash" value="428e3f5e04ba13af3d87fc0110188accfa5d3dbd4e9a2e796c16cc502b23a8b8"/></canvas></imgdir><imgdir name="eye"><canvas name="0" width="1" height="1"><vector name="origin" x="24" y="67"/><int name="z" value="0"/><string name="_inlink" value="condition/stand/0"/></canvas><canvas name="1" width="54" height="68"><vector name="origin" x="24" y="67"/><int name="z" value="0"/><string name="_hash" value="3351712fcf2975ed021b12521263a55dc85ac3d08f5387ed6ce8e15702354705"/></canvas><canvas name="2" width="54" height="68"><vector name="origin" x="24" y="67"/><int name="z" value="0"/><string name="_hash" value="1c30d597a609bc0c30f6aa2af7235e1b104eb945841d0aa744d7c08de16c2ee5"/></canvas><canvas name="3" width="1" height="1"><vector name="origin" x="24" y="67"/><int name="z" value="0"/><string name="_inlink" value="condition/eye/1"/></canvas></imgdir><imgdir name="say"><canvas name="0" width="1" height="1"><vector name="origin" x="24" y="67"/><int name="z" value="0"/><string name="_inlink" value="condition/stand/0"/></canvas><canvas name="1" width="54" height="68"><vector name="origin" x="24" y="67"/><int name="z" value="0"/><string name="_hash" value="ef666ecda6e563268b0be2382428a073439e06735c1cdfa4be33c0bb69eac32a"/></canvas><canvas name="2" width="54" height="68"><vector name="origin" x="24" y="67"/><int name="z" value="0"/><string name="_hash" value="07f13b0ef6d4224bc67aef169b52a91f357823403ea00c9a3c014aa13f2b0f9e"/></canvas><canvas name="3" width="54" height="68"><vector name="origin" x="24" y="67"/><int name="z" value="0"/><string name="_hash" value="c679340bf832823cd35bb5863b7831a2efb419e91c8d348eb5114d5819ab76a2"/></canvas><canvas name="4" width="54" height="68"><vector name="origin" x="24" y="67"/><int name="z" value="0"/><string name="_hash" value="6c7e33431b32b7c7164f6b33979798f9236d77b86e3b4421f2807d8ccbe94b94"/></canvas><canvas name="5" width="1" height="1"><vector name="origin" x="24" y="67"/><int name="z" value="0"/><string name="_inlink" value="condition/say/3"/></canvas><canvas name="6" width="1" height="1"><vector name="origin" x="24" y="67"/><int name="z" value="0"/><string name="_inlink" value="condition/say/2"/></canvas><canvas name="7" width="1" height="1"><vector name="origin" x="24" y="67"/><int name="z" value="0"/><string name="_inlink" value="condition/say/1"/></canvas></imgdir><uol name="move" value="../move"/></imgdir></imgdir>