<?xml version="1.0" encoding="UTF-8" standalone="yes"?><imgdir name="9400560.img"><imgdir name="info"><imgdir name="speak"><string name="0" value="n0"/><string name="1" value="n1"/></imgdir><imgdir name="script"><imgdir name="0"><string name="script" value="PLCX18_rescued"/></imgdir></imgdir><canvas name="default" width="129" height="83"><vector name="origin" x="64" y="82"/><string name="_hash" value="28744d26e6d6f55ec671e56728df1e631aae684d58d6002bbe1e8135994ec0f4"/></canvas></imgdir><imgdir name="stand"><canvas name="0" width="1" height="1"><vector name="origin" x="0" y="83"/><int name="delay" value="120"/></canvas></imgdir><imgdir name="condition1"><imgdir name="62486"><string name="value" value="1"/></imgdir><imgdir name="stand"><canvas name="0" width="1" height="1"><vector name="origin" x="0" y="0"/><int name="delay" value="120"/></canvas></imgdir><int name="hide" value="1"/></imgdir></imgdir>